setup.cfg
setup.py
Henosis/model.py
Henosis/server.py
Henosis/utils.py
Henosis.egg-info/PKG-INFO
Henosis.egg-info/SOURCES.txt
Henosis.egg-info/dependency_links.txt
Henosis.egg-info/requires.txt
Henosis.egg-info/top_level.txt