Metadata-Version: 1.1
Name: Henosis
Version: 0.0.10
Summary: A Python framework for deploying recommendation models for form fields.
Home-page: https://github.com/vc1492a/henosis
Author: Valentino Constantinou
Author-email: vc@valentino.io
License: Apache License, Version 2.0
Download-URL: https://github.com/vc1492a/henosis/archive/0.0.10.tar.gz
Keywords: recommendation,system,predictive,machine,learning,modeling,recommender,statistics
Platform: UNKNOWN
